odoo/addons/partner_category_multi_company/README.rst
odoo/addons/partner_category_multi_company/__init__.py
odoo/addons/partner_category_multi_company/__manifest__.py
odoo/addons/partner_category_multi_company/i18n/hr.po
odoo/addons/partner_category_multi_company/i18n/it.po
odoo/addons/partner_category_multi_company/i18n/partner_category_multi_company.pot
odoo/addons/partner_category_multi_company/i18n/pt.po
odoo/addons/partner_category_multi_company/i18n/res_partner_category_multi_company.pot
odoo/addons/partner_category_multi_company/models/__init__.py
odoo/addons/partner_category_multi_company/models/res_partner.py
odoo/addons/partner_category_multi_company/models/res_partner_category.py
odoo/addons/partner_category_multi_company/readme/CONTRIBUTORS.rst
odoo/addons/partner_category_multi_company/readme/DESCRIPTION.rst
odoo/addons/partner_category_multi_company/security/res_partner_category.xml
odoo/addons/partner_category_multi_company/static/description/icon.png
odoo/addons/partner_category_multi_company/static/description/index.html
odoo/addons/partner_category_multi_company/views/res_partner_category.xml
odoo/addons/partner_category_multi_company/views/res_partner_views.xml
odoo_addon_partner_category_multi_company-16.0.1.0.0.5.dist-info/METADATA
odoo_addon_partner_category_multi_company-16.0.1.0.0.5.dist-info/WHEEL
odoo_addon_partner_category_multi_company-16.0.1.0.0.5.dist-info/top_level.txt
odoo_addon_partner_category_multi_company-16.0.1.0.0.5.dist-info/RECORD
